pyipextract/__init__.py
pyipextract/pyipextract.py
pyipextract-1.0.2.dist-info/LICENSE
pyipextract-1.0.2.dist-info/METADATA
pyipextract-1.0.2.dist-info/WHEEL
pyipextract-1.0.2.dist-info/top_level.txt
pyipextract-1.0.2.dist-info/RECORD
