Metadata-Version: 2.1
Name: pyipextract
Version: 1.0.2
Summary: A Python utility to validate or extract IPv4 addresses from strings
Home-page: https://github.com/c0d3monk/pyipextract
Author: c0d3monk
Author-email: akr.optimus@gmail.com
License: Apache License 2.0
Platform: UNKNOWN
Classifier: Programming Language :: Python :: 3
Classifier: License :: OSI Approved :: Apache Software License
Classifier: Operating System :: OS Independent
Requires-Python: >=3.6
